{
  "updated_at": "2026-06-30T14:15:33.651180+00:00",
  "run_id": "2026-06-30-14h",
  "version": 6,
  "sources": [
    "Al Jazeera",
    "BBC News",
    "Bloomberg",
    "DW News",
    "Dinheiro Vivo",
    "Eco",
    "Euronews PT",
    "Fast Company",
    "Financial Times",
    "HBR",
    "Jornal de Negócios",
    "Le Monde EN",
    "MIT Sloan Review",
    "Negócios ao Minuto",
    "Observador",
    "Público",
    "RTP Notícias",
    "Reuters",
    "Reuters Business",
    "SAPO Tek",
    "SIC Notícias",
    "Seeking Alpha",
    "TechCrunch",
    "The Economist",
    "The Guardian",
    "The Verge",
    "Wired"
  ],
  "gemini_status": "failed",
  "user_source_errors": [],
  "gemini_alert": "O serviço de IA não respondeu neste run. Os artigos são mostrados sem tradução ou análise, categorizados automaticamente por fonte.",
  "articles": [
    {
      "title": "Manhunt after bomb injures Ukrainian oligarch in Monaco",
      "url": "https://www.bbc.co.uk/news/articles/cpv37wx03v7o?at_medium=RSS&at_campaign=rss",
      "source": "BBC News",
      "translated": false,
      "category": "breaking",
      "summary": "",
      "why": "",
      "impact": "",
      "impact_level": "médio",
      "breaking": false,
      "recomendacao": false,
      "enriched": false,
      "date": "2026-06-30T14:15:33.651180+00:00"
    },
    {
      "title": "Shetland backs plan to connect islands with £1.5bn undersea tunnels",
      "url": "https://www.bbc.co.uk/news/articles/cvgl1egyl79o?at_medium=RSS&at_campaign=rss",
      "source": "BBC News",
      "translated": false,
      "category": "breaking",
      "summary": "",
      "why": "",
      "impact": "",
      "impact_level": "médio",
      "breaking": false,
      "recomendacao": false,
      "enriched": false,
      "date": "2026-06-30T14:15:33.651180+00:00"
    },
    {
      "title": "Government promises to act after 'shocking' failings in maternity care in England",
      "url": "https://www.bbc.co.uk/news/articles/cddlgqpg7mzo?at_medium=RSS&at_campaign=rss",
      "source": "BBC News",
      "translated": false,
      "category": "breaking",
      "summary": "",
      "why": "",
      "impact": "",
      "impact_level": "médio",
      "breaking": false,
      "recomendacao": false,
      "enriched": false,
      "date": "2026-06-30T14:15:33.651180+00:00"
    },
    {
      "title": "China is a clear winner from Trump’s war in Middle East, report concludes",
      "url": "https://www.theguardian.com/world/2026/jun/30/china-clear-winner-trump-war-middle-east-report-iran-strait-of-hormuz",
      "source": "The Guardian",
      "translated": false,
      "category": "mundo",
      "summary": "",
      "why": "",
      "impact": "",
      "impact_level": "médio",
      "breaking": false,
      "recomendacao": false,
      "enriched": false,
      "date": "2026-06-30T14:15:33.651180+00:00"
    },
    {
      "title": "Thai police investigate if Australian man charged over 17-year-old girl’s murder linked to other unsolved cases",
      "url": "https://www.theguardian.com/world/2026/jun/30/thai-teen-girl-murder-australian-man-charged-police-investigate-other-unsolved-cases-ntwnfb",
      "source": "The Guardian",
      "translated": false,
      "category": "mundo",
      "summary": "",
      "why": "",
      "impact": "",
      "impact_level": "médio",
      "breaking": false,
      "recomendacao": false,
      "enriched": false,
      "date": "2026-06-30T14:15:33.651180+00:00"
    },
    {
      "title": "Police units deployed across South Africa before anti-immigration marches",
      "url": "https://www.theguardian.com/world/2026/jun/30/south-africa-police-anti-immigrant-protests",
      "source": "The Guardian",
      "translated": false,
      "category": "mundo",
      "summary": "",
      "why": "",
      "impact": "",
      "impact_level": "médio",
      "breaking": false,
      "recomendacao": false,
      "enriched": false,
      "date": "2026-06-30T14:15:33.651180+00:00"
    },
    {
      "title": "What privacy settings has WhatsApp changed?",
      "url": "https://www.aljazeera.com/news/2026/6/30/what-privacy-settings-has-whatsapp-changed?traffic_source=rss",
      "source": "Al Jazeera",
      "translated": false,
      "category": "mundo",
      "summary": "",
      "why": "",
      "impact": "",
      "impact_level": "médio",
      "breaking": false,
      "recomendacao": false,
      "enriched": false,
      "date": "2026-06-30T14:15:33.651180+00:00"
    },
    {
      "title": "US envoys in Doha for indirect talks with Iranian technical delegation",
      "url": "https://www.aljazeera.com/news/2026/6/30/us-envoys-in-doha-for-indirect-talks-with-iranian-technical-delegation?traffic_source=rss",
      "source": "Al Jazeera",
      "translated": false,
      "category": "mundo",
      "summary": "",
      "why": "",
      "impact": "",
      "impact_level": "médio",
      "breaking": false,
      "recomendacao": false,
      "enriched": false,
      "date": "2026-06-30T14:15:33.651180+00:00"
    },
    {
      "title": "UK’s Starmer announces 300-billion-pound defence investment plan",
      "url": "https://www.aljazeera.com/economy/2026/6/30/uks-starmer-announces-300-billion-pound-defence-investment-plan?traffic_source=rss",
      "source": "Al Jazeera",
      "translated": false,
      "category": "mundo",
      "summary": "",
      "why": "",
      "impact": "",
      "impact_level": "médio",
      "breaking": false,
      "recomendacao": false,
      "enriched": false,
      "date": "2026-06-30T14:15:33.651180+00:00"
    },
    {
      "title": "África do Sul: manifestantes exigem saída de migrantes sem documentos",
      "url": "http://pt.euronews.com/video/2026/06/30/africa-do-sul-manifestantes-exigem-saida-de-migrantes-sem-documentos",
      "source": "Euronews PT",
      "translated": false,
      "category": "mundo",
      "summary": "",
      "why": "",
      "impact": "",
      "impact_level": "médio",
      "breaking": false,
      "recomendacao": false,
      "enriched": false,
      "date": "2026-06-30T14:15:33.651180+00:00"
    },
    {
      "title": "Espanha: milhares banhados em vinho em festival icónico",
      "url": "http://pt.euronews.com/video/2026/06/30/espanha-milhares-banhados-em-vinho-em-festival-iconico",
      "source": "Euronews PT",
      "translated": false,
      "category": "mundo",
      "summary": "",
      "why": "",
      "impact": "",
      "impact_level": "médio",
      "breaking": false,
      "recomendacao": false,
      "enriched": false,
      "date": "2026-06-30T14:15:33.651180+00:00"
    },
    {
      "title": "Enviados dos EUA Witkoff e Kushner chegam ao Qatar para novas conversações sobre Irão",
      "url": "http://pt.euronews.com/2026/06/30/enviados-dos-eua-witkoff-e-kushner-chegam-ao-qatar-para-novas-conversacoes-sobre-irao",
      "source": "Euronews PT",
      "translated": false,
      "category": "mundo",
      "summary": "",
      "why": "",
      "impact": "",
      "impact_level": "médio",
      "breaking": false,
      "recomendacao": false,
      "enriched": false,
      "date": "2026-06-30T14:15:33.651180+00:00"
    },
    {
      "title": "E a mãe, já pensou na lápide que gostava para si?",
      "url": "https://www.publico.pt/2026/06/30/impar/cronica/mae-ja-pensou-lapide-gostava-2179989",
      "source": "Público",
      "translated": false,
      "category": "portugal",
      "summary": "",
      "why": "",
      "impact": "",
      "impact_level": "médio",
      "breaking": false,
      "recomendacao": false,
      "enriched": false,
      "date": "2026-06-30T14:15:33.651180+00:00"
    },
    {
      "title": "Quase um quarto das mulheres que trabalham alterou a vida profissional para conciliar com a familiar",
      "url": "https://www.publico.pt/2026/06/30/sociedade/noticia/quase-quarto-mulheres-trabalham-alterou-vida-profissional-conciliar-familiar-2179982",
      "source": "Público",
      "translated": false,
      "category": "portugal",
      "summary": "",
      "why": "",
      "impact": "",
      "impact_level": "médio",
      "breaking": false,
      "recomendacao": false,
      "enriched": false,
      "date": "2026-06-30T14:15:33.651180+00:00"
    },
    {
      "title": "Venezuela suspende por 48 horas acesso de jornalistas estrangeiros a La Guaira",
      "url": "https://www.publico.pt/2026/06/30/mundo/noticia/venezuela-suspende-48-horas-acesso-jornalistas-estrangeiros-guaira-2179991",
      "source": "Público",
      "translated": false,
      "category": "portugal",
      "summary": "",
      "why": "",
      "impact": "",
      "impact_level": "médio",
      "breaking": false,
      "recomendacao": false,
      "enriched": false,
      "date": "2026-06-30T14:15:33.651180+00:00"
    },
    {
      "title": "Grande Entrevista - Sinfonia",
      "url": "http://observador21.blogspot.com/2010/03/grande-entrevista-sinfonia.html",
      "source": "Observador",
      "translated": false,
      "category": "portugal",
      "summary": "",
      "why": "",
      "impact": "",
      "impact_level": "médio",
      "breaking": false,
      "recomendacao": false,
      "enriched": false,
      "date": "2026-06-30T14:15:33.651180+00:00"
    },
    {
      "title": "Curtas: Arbitragem I",
      "url": "http://observador21.blogspot.com/2010/02/curtas-arbitragem-i.html",
      "source": "Observador",
      "translated": false,
      "category": "portugal",
      "summary": "",
      "why": "",
      "impact": "",
      "impact_level": "médio",
      "breaking": false,
      "recomendacao": false,
      "enriched": false,
      "date": "2026-06-30T14:15:33.651180+00:00"
    },
    {
      "title": "Curtas: Vitor Constâncio II",
      "url": "http://observador21.blogspot.com/2010/02/curtas-vitor-constancio-ii.html",
      "source": "Observador",
      "translated": false,
      "category": "portugal",
      "summary": "",
      "why": "",
      "impact": "",
      "impact_level": "médio",
      "breaking": false,
      "recomendacao": false,
      "enriched": false,
      "date": "2026-06-30T14:15:33.651180+00:00"
    },
    {
      "title": "Replimune: Stock Buoyant On Third Try At RP1 Approval - FDA AdCom May Be Crucial",
      "url": "https://seekingalpha.com/article/4918850-replimune-stock-buoyant-on-third-try-at-rp1-approval-fda-adcom-may-be-crucial?source=feed_all_articles",
      "source": "Seeking Alpha",
      "translated": false,
      "category": "portfolio",
      "summary": "",
      "why": "",
      "impact": "",
      "impact_level": "médio",
      "breaking": false,
      "recomendacao": false,
      "enriched": false,
      "date": "2026-06-30T14:15:33.651180+00:00"
    },
    {
      "title": "Thungela Resources Limited (TNGRF) Discusses Pre-Close Update, Market Impacts of Middle East Conflict, and Coal Price Trends Transcript",
      "url": "https://seekingalpha.com/article/4918808-thungela-resources-limited-tngrf-discusses-pre-close-update-market-impacts-of-middle-east?source=feed_all_articles",
      "source": "Seeking Alpha",
      "translated": false,
      "category": "portfolio",
      "summary": "",
      "why": "",
      "impact": "",
      "impact_level": "médio",
      "breaking": false,
      "recomendacao": false,
      "enriched": false,
      "date": "2026-06-30T14:15:33.651180+00:00"
    },
    {
      "title": "Nickel Miners News For The Month Of June 2026",
      "url": "https://seekingalpha.com/article/4918849-nickel-miners-news-for-month-of-june-2026?source=feed_all_articles",
      "source": "Seeking Alpha",
      "translated": false,
      "category": "portfolio",
      "summary": "",
      "why": "",
      "impact": "",
      "impact_level": "médio",
      "breaking": false,
      "recomendacao": false,
      "enriched": false,
      "date": "2026-06-30T14:15:33.651180+00:00"
    },
    {
      "title": "France records an extra 300 deaths during May heatwave",
      "url": "https://www.lemonde.fr/en/health/article/2026/06/30/france-records-an-extra-300-deaths-during-may-heatwave_6755011_14.html",
      "source": "Le Monde EN",
      "translated": false,
      "category": "mundo",
      "summary": "",
      "why": "",
      "impact": "",
      "impact_level": "médio",
      "breaking": false,
      "recomendacao": false,
      "enriched": false,
      "date": "2026-06-30T14:15:33.651180+00:00"
    },
    {
      "title": "Serena Williams returns to Wimbledon, in a comeback raising questions",
      "url": "https://www.lemonde.fr/en/sports/article/2026/06/30/serena-williams-returns-to-wimbledon-in-a-comeback-raising-questions_6755008_9.html",
      "source": "Le Monde EN",
      "translated": false,
      "category": "mundo",
      "summary": "",
      "why": "",
      "impact": "",
      "impact_level": "médio",
      "breaking": false,
      "recomendacao": false,
      "enriched": false,
      "date": "2026-06-30T14:15:33.651180+00:00"
    },
    {
      "title": "EU to implement trade deal with US starting Wednesday",
      "url": "https://www.lemonde.fr/en/international/article/2026/06/30/eu-to-implement-trade-deal-with-us-starting-wednesday_6755007_4.html",
      "source": "Le Monde EN",
      "translated": false,
      "category": "mundo",
      "summary": "",
      "why": "",
      "impact": "",
      "impact_level": "médio",
      "breaking": false,
      "recomendacao": false,
      "enriched": false,
      "date": "2026-06-30T14:15:33.651180+00:00"
    },
    {
      "title": "Your brand deserves its own stage — Side Events at TechCrunch Disrupt 2026",
      "url": "https://techcrunch.com/2026/06/30/your-brand-deserves-its-own-stage-side-events-at-techcrunch-disrupt-2026/",
      "source": "TechCrunch",
      "translated": false,
      "category": "tecnologia",
      "summary": "",
      "why": "",
      "impact": "",
      "impact_level": "médio",
      "breaking": false,
      "recomendacao": false,
      "enriched": false,
      "date": "2026-06-30T14:15:33.651180+00:00"
    },
    {
      "title": "Lumo, Proton’s privacy-focused AI chatbot, gets an upgrade",
      "url": "https://techcrunch.com/2026/06/30/lumo-protons-privacy-focused-ai-chatbot-gets-an-upgrade/",
      "source": "TechCrunch",
      "translated": false,
      "category": "tecnologia",
      "summary": "",
      "why": "",
      "impact": "",
      "impact_level": "médio",
      "breaking": false,
      "recomendacao": false,
      "enriched": false,
      "date": "2026-06-30T14:15:33.651180+00:00"
    },
    {
      "title": "Crypto exchange OKX wants AI agents to hire and pay each other",
      "url": "https://techcrunch.com/2026/06/30/crypto-exchange-okx-wants-ai-agents-to-hire-and-pay-each-other/",
      "source": "TechCrunch",
      "translated": false,
      "category": "tecnologia",
      "summary": "",
      "why": "",
      "impact": "",
      "impact_level": "médio",
      "breaking": false,
      "recomendacao": false,
      "enriched": false,
      "date": "2026-06-30T14:15:33.651180+00:00"
    },
    {
      "title": "Turkey’s economic plan to win from the Iran war",
      "url": "https://www.economist.com/finance-and-economics/2026/06/29/turkeys-economic-plan-to-win-from-the-iran-war",
      "source": "The Economist",
      "translated": false,
      "category": "economia",
      "summary": "",
      "why": "",
      "impact": "",
      "impact_level": "médio",
      "breaking": false,
      "recomendacao": false,
      "enriched": false,
      "date": "2026-06-30T14:15:33.651180+00:00"
    },
    {
      "title": "China cracks down on rule-bending offshore investments",
      "url": "https://www.economist.com/finance-and-economics/2026/06/28/china-cracks-down-on-rule-bending-offshore-investments",
      "source": "The Economist",
      "translated": false,
      "category": "economia",
      "summary": "",
      "why": "",
      "impact": "",
      "impact_level": "médio",
      "breaking": false,
      "recomendacao": false,
      "enriched": false,
      "date": "2026-06-30T14:15:33.651180+00:00"
    },
    {
      "title": "Will AI lower interest rates?",
      "url": "https://www.economist.com/finance-and-economics/2026/06/25/will-ai-lower-interest-rates",
      "source": "The Economist",
      "translated": false,
      "category": "economia",
      "summary": "",
      "why": "",
      "impact": "",
      "impact_level": "médio",
      "breaking": false,
      "recomendacao": false,
      "enriched": false,
      "date": "2026-06-30T14:15:33.651180+00:00"
    },
    {
      "title": "US birthright citizenship: What changes if it's removed?",
      "url": "https://www.dw.com/en/us-birthright-citizenship-what-changes-if-it-s-removed/a-77773604?maca=en-rss-en-all-1573-rdf",
      "source": "DW News",
      "translated": false,
      "category": "mundo",
      "summary": "",
      "why": "",
      "impact": "",
      "impact_level": "médio",
      "breaking": false,
      "recomendacao": false,
      "enriched": false,
      "date": "2026-06-30T14:15:33.651180+00:00"
    },
    {
      "title": "'Under siege': Uganda's army chief clamps down on the press",
      "url": "https://www.dw.com/en/under-siege-uganda-s-army-chief-clamps-down-on-the-press/a-77769666?maca=en-rss-en-all-1573-rdf",
      "source": "DW News",
      "translated": false,
      "category": "mundo",
      "summary": "",
      "why": "",
      "impact": "",
      "impact_level": "médio",
      "breaking": false,
      "recomendacao": false,
      "enriched": false,
      "date": "2026-06-30T14:15:33.651180+00:00"
    },
    {
      "title": "Will alleged crime ties damage Serbia's ruling party?",
      "url": "https://www.dw.com/en/will-alleged-crime-ties-damage-serbia-s-ruling-party/a-77772788?maca=en-rss-en-all-1573-rdf",
      "source": "DW News",
      "translated": false,
      "category": "mundo",
      "summary": "",
      "why": "",
      "impact": "",
      "impact_level": "médio",
      "breaking": false,
      "recomendacao": false,
      "enriched": false,
      "date": "2026-06-30T14:15:33.651180+00:00"
    },
    {
      "title": "Schwab CEO on Why They Keep Fees Low",
      "url": "https://www.bloomberg.com/news/videos/2026-06-30/schwab-ceo-on-why-they-keep-fees-low-video",
      "source": "Bloomberg",
      "translated": false,
      "category": "economia",
      "summary": "",
      "why": "",
      "impact": "",
      "impact_level": "médio",
      "breaking": false,
      "recomendacao": false,
      "enriched": false,
      "date": "2026-06-30T14:15:33.651180+00:00"
    },
    {
      "title": "US Stocks Mixed as Indexes Head for Best Quarter Since 2020",
      "url": "https://www.bloomberg.com/news/articles/2026-06-30/us-stocks-mixed-as-indexes-head-for-best-quarter-since-2020",
      "source": "Bloomberg",
      "translated": false,
      "category": "economia",
      "summary": "",
      "why": "",
      "impact": "",
      "impact_level": "médio",
      "breaking": false,
      "recomendacao": false,
      "enriched": false,
      "date": "2026-06-30T14:15:33.651180+00:00"
    },
    {
      "title": "UK ‘Minded to Intervene’ in Paramount’s Warner Bros. Deal Over Media Ownership Concerns",
      "url": "https://www.bloomberg.com/news/articles/2026-06-30/uk-minded-to-intervene-in-paramount-s-deal-for-warner-bros",
      "source": "Bloomberg",
      "translated": false,
      "category": "economia",
      "summary": "",
      "why": "",
      "impact": "",
      "impact_level": "médio",
      "breaking": false,
      "recomendacao": false,
      "enriched": false,
      "date": "2026-06-30T14:15:33.651180+00:00"
    },
    {
      "title": "The 2 Best Slushie Machines of 2026: Now With Soft Serve",
      "url": "https://www.wired.com/gallery/best-slushie-machines/",
      "source": "Wired",
      "translated": false,
      "category": "tecnologia",
      "summary": "",
      "why": "",
      "impact": "",
      "impact_level": "médio",
      "breaking": false,
      "recomendacao": false,
      "enriched": false,
      "date": "2026-06-30T14:15:33.651180+00:00"
    },
    {
      "title": "Bitdefender VPN Review: Fast and Affordable Privacy",
      "url": "https://www.wired.com/review/bitdefender-vpn/",
      "source": "Wired",
      "translated": false,
      "category": "tecnologia",
      "summary": "",
      "why": "",
      "impact": "",
      "impact_level": "médio",
      "breaking": false,
      "recomendacao": false,
      "enriched": false,
      "date": "2026-06-30T14:15:33.651180+00:00"
    },
    {
      "title": "Bernie Sanders Saw This Coming",
      "url": "https://www.wired.com/story/the-big-interview-podcast-senator-bernie-sanders/",
      "source": "Wired",
      "translated": false,
      "category": "tecnologia",
      "summary": "",
      "why": "",
      "impact": "",
      "impact_level": "médio",
      "breaking": false,
      "recomendacao": false,
      "enriched": false,
      "date": "2026-06-30T14:15:33.651180+00:00"
    },
    {
      "title": "iPhone 18 Pro ‘drop test’ leaks get yanked from X",
      "url": "https://www.theverge.com/tech/959474/iphone-18-pro-leaked-videos-pulled",
      "source": "The Verge",
      "translated": false,
      "category": "tecnologia",
      "summary": "",
      "why": "",
      "impact": "",
      "impact_level": "médio",
      "breaking": false,
      "recomendacao": false,
      "enriched": false,
      "date": "2026-06-30T14:15:33.651180+00:00"
    },
    {
      "title": "Meet the lawyer who beat Elon Musk — twice",
      "url": "https://www.theverge.com/column/959270/elon-musk-open-ai-bill-savitt-twitter",
      "source": "The Verge",
      "translated": false,
      "category": "tecnologia",
      "summary": "",
      "why": "",
      "impact": "",
      "impact_level": "médio",
      "breaking": false,
      "recomendacao": false,
      "enriched": false,
      "date": "2026-06-30T14:15:33.651180+00:00"
    },
    {
      "title": "This motor could be the future of e-bikes",
      "url": "https://www.theverge.com/news/959382/avinox-mg-concept-gobao-mgu-ecvt",
      "source": "The Verge",
      "translated": false,
      "category": "tecnologia",
      "summary": "",
      "why": "",
      "impact": "",
      "impact_level": "médio",
      "breaking": false,
      "recomendacao": false,
      "enriched": false,
      "date": "2026-06-30T14:15:33.651180+00:00"
    },
    {
      "title": "Qatar nega a existência de negociações diretas entre Irão e Estados Unidos nos próximos dias",
      "url": "https://www.dn.pt/internacional/qatar-nega-a-existncia-de-negociaes-diretas-entre-iro-e-estados-unidos-nos-prximos-dias",
      "source": "Dinheiro Vivo",
      "translated": false,
      "category": "economia",
      "summary": "",
      "why": "",
      "impact": "",
      "impact_level": "médio",
      "breaking": false,
      "recomendacao": false,
      "enriched": false,
      "date": "2026-06-30T14:15:33.651180+00:00"
    },
    {
      "title": "Pesquisa revela que jovens brasileiros desconhecem a política sem redes sociais",
      "url": "https://dnbrasil.dn.pt/pesquisa-revela-que-jovens-brasileiros-desconhecem-a-poltica-sem-redes-sociais",
      "source": "Dinheiro Vivo",
      "translated": false,
      "category": "economia",
      "summary": "",
      "why": "",
      "impact": "",
      "impact_level": "médio",
      "breaking": false,
      "recomendacao": false,
      "enriched": false,
      "date": "2026-06-30T14:15:33.651180+00:00"
    },
    {
      "title": "PSP tem novos oficiais",
      "url": "https://www.dn.pt/sociedade/psp-tem-novos-oficiais",
      "source": "Dinheiro Vivo",
      "translated": false,
      "category": "economia",
      "summary": "",
      "why": "",
      "impact": "",
      "impact_level": "médio",
      "breaking": false,
      "recomendacao": false,
      "enriched": false,
      "date": "2026-06-30T14:15:33.651180+00:00"
    },
    {
      "title": "Wall Street arranca dividida à espera de maior definição sobre Irão",
      "url": "https://www.jornaldenegocios.pt/mercados/mercados-num-minuto/detalhe/recuperacao-em-wall-street-anima-indices-asiaticos-tiveram-melhor-trimestre-em-quase-17-anos",
      "source": "Jornal de Negócios",
      "translated": false,
      "category": "economia",
      "summary": "",
      "why": "",
      "impact": "",
      "impact_level": "médio",
      "breaking": false,
      "recomendacao": false,
      "enriched": false,
      "date": "2026-06-30T14:15:33.651180+00:00"
    },
    {
      "title": "Euforia na IA? Bolha só se os lucros não acompanharem mega-investimentos",
      "url": "https://www.jornaldenegocios.pt/mercados/bolsa/detalhe/euforia-na-ia-bolha-so-se-os-lucros-nao-acompanharem-mega-investimentos",
      "source": "Jornal de Negócios",
      "translated": false,
      "category": "economia",
      "summary": "",
      "why": "",
      "impact": "",
      "impact_level": "médio",
      "breaking": false,
      "recomendacao": false,
      "enriched": false,
      "date": "2026-06-30T14:15:33.651180+00:00"
    },
    {
      "title": "O Negócios pergunta. Maioria concorda com a criação de um fundo soberano português",
      "url": "https://www.jornaldenegocios.pt/empresas/media/o-negocios/detalhe/o-negocios-pergunta-maioria-concorda-com-a-criacao-de-um-fundo-soberano-portugues",
      "source": "Jornal de Negócios",
      "translated": false,
      "category": "economia",
      "summary": "",
      "why": "",
      "impact": "",
      "impact_level": "médio",
      "breaking": false,
      "recomendacao": false,
      "enriched": false,
      "date": "2026-06-30T14:15:33.651180+00:00"
    },
    {
      "title": "Carneiro diz que há casas prontas à espera “de um novo ciclo eleitoral” para serem entregues",
      "url": "https://eco.sapo.pt/2026/06/30/carneiro-diz-que-ha-casas-prontas-a-espera-de-um-novo-ciclo-eleitoral-para-serem-entregues/",
      "source": "Eco",
      "translated": false,
      "category": "portugal",
      "summary": "",
      "why": "",
      "impact": "",
      "impact_level": "médio",
      "breaking": false,
      "recomendacao": false,
      "enriched": false,
      "date": "2026-06-30T14:15:33.651180+00:00"
    },
    {
      "title": "Governo dos Açores diz que projeto da semana de quatro dias decorreu com tranquilidade",
      "url": "https://eco.sapo.pt/2026/06/30/governo-dos-acores-diz-que-projeto-da-semana-de-quatro-dias-decorreu-com-tranquilidade/",
      "source": "Eco",
      "translated": false,
      "category": "portugal",
      "summary": "",
      "why": "",
      "impact": "",
      "impact_level": "médio",
      "breaking": false,
      "recomendacao": false,
      "enriched": false,
      "date": "2026-06-30T14:15:33.651180+00:00"
    },
    {
      "title": "5 coisas a saber sobre a nova lista de produtos de defesa",
      "url": "https://eco.sapo.pt/opiniao/5-coisas-a-saber-sobre-a-nova-lista-de-produtos-de-defesa/",
      "source": "Eco",
      "translated": false,
      "category": "portugal",
      "summary": "",
      "why": "",
      "impact": "",
      "impact_level": "médio",
      "breaking": false,
      "recomendacao": false,
      "enriched": false,
      "date": "2026-06-30T14:15:33.651180+00:00"
    },
    {
      "title": "Will tech giants ever let us opt out of AI search features?",
      "url": "https://www.fastcompany.com/91561463/google-ai-overviews-users-opt-out-will-that-change",
      "source": "Fast Company",
      "translated": false,
      "category": "carreira",
      "summary": "",
      "why": "",
      "impact": "",
      "impact_level": "médio",
      "breaking": false,
      "recomendacao": false,
      "enriched": false,
      "date": "2026-06-30T14:15:33.651180+00:00"
    },
    {
      "title": "Here’s how to reserve your WhatsApp username—and why you should do it before the release date",
      "url": "https://www.fastcompany.com/91567304/whatsapp-usernames-release-date-nears-how-to-reserve-yours",
      "source": "Fast Company",
      "translated": false,
      "category": "carreira",
      "summary": "",
      "why": "",
      "impact": "",
      "impact_level": "médio",
      "breaking": false,
      "recomendacao": false,
      "enriched": false,
      "date": "2026-06-30T14:15:33.651180+00:00"
    },
    {
      "title": "How to Ensure Your Next CEO is Always in the Room",
      "url": "https://www.fastcompany.com/91566039/how-to-ensure-your-next-ceo-is-always-in-the-room",
      "source": "Fast Company",
      "translated": false,
      "category": "carreira",
      "summary": "",
      "why": "",
      "impact": "",
      "impact_level": "médio",
      "breaking": false,
      "recomendacao": false,
      "enriched": false,
      "date": "2026-06-30T14:15:33.651180+00:00"
    },
    {
      "title": "Ukrainian tycoon injured in Monaco bomb attack",
      "url": "https://www.ft.com/content/7455e85b-7389-49dd-b7c8-f145f79e7f0b",
      "source": "Financial Times",
      "translated": false,
      "category": "economia",
      "summary": "",
      "why": "",
      "impact": "",
      "impact_level": "médio",
      "breaking": false,
      "recomendacao": false,
      "enriched": false,
      "date": "2026-06-30T14:15:33.651180+00:00"
    },
    {
      "title": "Ukraine argues it can legally attack Russia’s shadow fleet",
      "url": "https://www.ft.com/content/d0f82c05-c35f-4e0f-b452-f61dc8a7e697",
      "source": "Financial Times",
      "translated": false,
      "category": "economia",
      "summary": "",
      "why": "",
      "impact": "",
      "impact_level": "médio",
      "breaking": false,
      "recomendacao": false,
      "enriched": false,
      "date": "2026-06-30T14:15:33.651180+00:00"
    },
    {
      "title": "Gold heads for worst quarter in more than a decade as retail frenzy fades",
      "url": "https://www.ft.com/content/ca75b117-f085-45be-95c1-7397d3b0797a",
      "source": "Financial Times",
      "translated": false,
      "category": "economia",
      "summary": "",
      "why": "",
      "impact": "",
      "impact_level": "médio",
      "breaking": false,
      "recomendacao": false,
      "enriched": false,
      "date": "2026-06-30T14:15:33.651180+00:00"
    },
    {
      "title": "When Evaluating an M&A Opportunity, Consider the Broader Digital Ecosystem",
      "url": "/2026/06/when-evaluating-an-ma-opportunity-consider-the-broader-digital-ecosystem",
      "source": "HBR",
      "translated": false,
      "category": "carreira",
      "summary": "",
      "why": "",
      "impact": "",
      "impact_level": "médio",
      "breaking": false,
      "recomendacao": false,
      "enriched": false,
      "date": "2026-06-30T14:15:33.651180+00:00"
    },
    {
      "title": "How Top World Cup, NBA, and NFL Coaches Make Better Decisions Under Pressure",
      "url": "/podcast/2026/06/how-top-world-cup-nba-and-nfl-coaches-make-better-decisions-under-pressure",
      "source": "HBR",
      "translated": false,
      "category": "carreira",
      "summary": "",
      "why": "",
      "impact": "",
      "impact_level": "médio",
      "breaking": false,
      "recomendacao": false,
      "enriched": false,
      "date": "2026-06-30T14:15:33.651180+00:00"
    },
    {
      "title": "Your Talent Strategy Has to Keep Up with Your AI Transformation",
      "url": "/2026/06/your-talent-strategy-has-to-keep-up-with-your-ai-transformation",
      "source": "HBR",
      "translated": false,
      "category": "carreira",
      "summary": "",
      "why": "",
      "impact": "",
      "impact_level": "médio",
      "breaking": false,
      "recomendacao": false,
      "enriched": false,
      "date": "2026-06-30T14:15:33.651180+00:00"
    }
  ],
  "categories": {
    "breaking": [
      {
        "title": "Manhunt after bomb injures Ukrainian oligarch in Monaco",
        "url": "https://www.bbc.co.uk/news/articles/cpv37wx03v7o?at_medium=RSS&at_campaign=rss",
        "source": "BBC News",
        "translated": false,
        "category": "breaking",
        "summary": "",
        "why": "",
        "impact": "",
        "impact_level": "médio",
        "breaking": false,
        "recomendacao": false,
        "enriched": false,
        "date": "2026-06-30T14:15:33.651180+00:00"
      },
      {
        "title": "Shetland backs plan to connect islands with £1.5bn undersea tunnels",
        "url": "https://www.bbc.co.uk/news/articles/cvgl1egyl79o?at_medium=RSS&at_campaign=rss",
        "source": "BBC News",
        "translated": false,
        "category": "breaking",
        "summary": "",
        "why": "",
        "impact": "",
        "impact_level": "médio",
        "breaking": false,
        "recomendacao": false,
        "enriched": false,
        "date": "2026-06-30T14:15:33.651180+00:00"
      },
      {
        "title": "Government promises to act after 'shocking' failings in maternity care in England",
        "url": "https://www.bbc.co.uk/news/articles/cddlgqpg7mzo?at_medium=RSS&at_campaign=rss",
        "source": "BBC News",
        "translated": false,
        "category": "breaking",
        "summary": "",
        "why": "",
        "impact": "",
        "impact_level": "médio",
        "breaking": false,
        "recomendacao": false,
        "enriched": false,
        "date": "2026-06-30T14:15:33.651180+00:00"
      }
    ],
    "portugal": [
      {
        "title": "E a mãe, já pensou na lápide que gostava para si?",
        "url": "https://www.publico.pt/2026/06/30/impar/cronica/mae-ja-pensou-lapide-gostava-2179989",
        "source": "Público",
        "translated": false,
        "category": "portugal",
        "summary": "",
        "why": "",
        "impact": "",
        "impact_level": "médio",
        "breaking": false,
        "recomendacao": false,
        "enriched": false,
        "date": "2026-06-30T14:15:33.651180+00:00"
      },
      {
        "title": "Quase um quarto das mulheres que trabalham alterou a vida profissional para conciliar com a familiar",
        "url": "https://www.publico.pt/2026/06/30/sociedade/noticia/quase-quarto-mulheres-trabalham-alterou-vida-profissional-conciliar-familiar-2179982",
        "source": "Público",
        "translated": false,
        "category": "portugal",
        "summary": "",
        "why": "",
        "impact": "",
        "impact_level": "médio",
        "breaking": false,
        "recomendacao": false,
        "enriched": false,
        "date": "2026-06-30T14:15:33.651180+00:00"
      },
      {
        "title": "Venezuela suspende por 48 horas acesso de jornalistas estrangeiros a La Guaira",
        "url": "https://www.publico.pt/2026/06/30/mundo/noticia/venezuela-suspende-48-horas-acesso-jornalistas-estrangeiros-guaira-2179991",
        "source": "Público",
        "translated": false,
        "category": "portugal",
        "summary": "",
        "why": "",
        "impact": "",
        "impact_level": "médio",
        "breaking": false,
        "recomendacao": false,
        "enriched": false,
        "date": "2026-06-30T14:15:33.651180+00:00"
      },
      {
        "title": "Grande Entrevista - Sinfonia",
        "url": "http://observador21.blogspot.com/2010/03/grande-entrevista-sinfonia.html",
        "source": "Observador",
        "translated": false,
        "category": "portugal",
        "summary": "",
        "why": "",
        "impact": "",
        "impact_level": "médio",
        "breaking": false,
        "recomendacao": false,
        "enriched": false,
        "date": "2026-06-30T14:15:33.651180+00:00"
      },
      {
        "title": "Curtas: Arbitragem I",
        "url": "http://observador21.blogspot.com/2010/02/curtas-arbitragem-i.html",
        "source": "Observador",
        "translated": false,
        "category": "portugal",
        "summary": "",
        "why": "",
        "impact": "",
        "impact_level": "médio",
        "breaking": false,
        "recomendacao": false,
        "enriched": false,
        "date": "2026-06-30T14:15:33.651180+00:00"
      },
      {
        "title": "Curtas: Vitor Constâncio II",
        "url": "http://observador21.blogspot.com/2010/02/curtas-vitor-constancio-ii.html",
        "source": "Observador",
        "translated": false,
        "category": "portugal",
        "summary": "",
        "why": "",
        "impact": "",
        "impact_level": "médio",
        "breaking": false,
        "recomendacao": false,
        "enriched": false,
        "date": "2026-06-30T14:15:33.651180+00:00"
      },
      {
        "title": "Carneiro diz que há casas prontas à espera “de um novo ciclo eleitoral” para serem entregues",
        "url": "https://eco.sapo.pt/2026/06/30/carneiro-diz-que-ha-casas-prontas-a-espera-de-um-novo-ciclo-eleitoral-para-serem-entregues/",
        "source": "Eco",
        "translated": false,
        "category": "portugal",
        "summary": "",
        "why": "",
        "impact": "",
        "impact_level": "médio",
        "breaking": false,
        "recomendacao": false,
        "enriched": false,
        "date": "2026-06-30T14:15:33.651180+00:00"
      },
      {
        "title": "Governo dos Açores diz que projeto da semana de quatro dias decorreu com tranquilidade",
        "url": "https://eco.sapo.pt/2026/06/30/governo-dos-acores-diz-que-projeto-da-semana-de-quatro-dias-decorreu-com-tranquilidade/",
        "source": "Eco",
        "translated": false,
        "category": "portugal",
        "summary": "",
        "why": "",
        "impact": "",
        "impact_level": "médio",
        "breaking": false,
        "recomendacao": false,
        "enriched": false,
        "date": "2026-06-30T14:15:33.651180+00:00"
      },
      {
        "title": "5 coisas a saber sobre a nova lista de produtos de defesa",
        "url": "https://eco.sapo.pt/opiniao/5-coisas-a-saber-sobre-a-nova-lista-de-produtos-de-defesa/",
        "source": "Eco",
        "translated": false,
        "category": "portugal",
        "summary": "",
        "why": "",
        "impact": "",
        "impact_level": "médio",
        "breaking": false,
        "recomendacao": false,
        "enriched": false,
        "date": "2026-06-30T14:15:33.651180+00:00"
      }
    ],
    "mundo": [
      {
        "title": "China is a clear winner from Trump’s war in Middle East, report concludes",
        "url": "https://www.theguardian.com/world/2026/jun/30/china-clear-winner-trump-war-middle-east-report-iran-strait-of-hormuz",
        "source": "The Guardian",
        "translated": false,
        "category": "mundo",
        "summary": "",
        "why": "",
        "impact": "",
        "impact_level": "médio",
        "breaking": false,
        "recomendacao": false,
        "enriched": false,
        "date": "2026-06-30T14:15:33.651180+00:00"
      },
      {
        "title": "Thai police investigate if Australian man charged over 17-year-old girl’s murder linked to other unsolved cases",
        "url": "https://www.theguardian.com/world/2026/jun/30/thai-teen-girl-murder-australian-man-charged-police-investigate-other-unsolved-cases-ntwnfb",
        "source": "The Guardian",
        "translated": false,
        "category": "mundo",
        "summary": "",
        "why": "",
        "impact": "",
        "impact_level": "médio",
        "breaking": false,
        "recomendacao": false,
        "enriched": false,
        "date": "2026-06-30T14:15:33.651180+00:00"
      },
      {
        "title": "Police units deployed across South Africa before anti-immigration marches",
        "url": "https://www.theguardian.com/world/2026/jun/30/south-africa-police-anti-immigrant-protests",
        "source": "The Guardian",
        "translated": false,
        "category": "mundo",
        "summary": "",
        "why": "",
        "impact": "",
        "impact_level": "médio",
        "breaking": false,
        "recomendacao": false,
        "enriched": false,
        "date": "2026-06-30T14:15:33.651180+00:00"
      },
      {
        "title": "What privacy settings has WhatsApp changed?",
        "url": "https://www.aljazeera.com/news/2026/6/30/what-privacy-settings-has-whatsapp-changed?traffic_source=rss",
        "source": "Al Jazeera",
        "translated": false,
        "category": "mundo",
        "summary": "",
        "why": "",
        "impact": "",
        "impact_level": "médio",
        "breaking": false,
        "recomendacao": false,
        "enriched": false,
        "date": "2026-06-30T14:15:33.651180+00:00"
      },
      {
        "title": "US envoys in Doha for indirect talks with Iranian technical delegation",
        "url": "https://www.aljazeera.com/news/2026/6/30/us-envoys-in-doha-for-indirect-talks-with-iranian-technical-delegation?traffic_source=rss",
        "source": "Al Jazeera",
        "translated": false,
        "category": "mundo",
        "summary": "",
        "why": "",
        "impact": "",
        "impact_level": "médio",
        "breaking": false,
        "recomendacao": false,
        "enriched": false,
        "date": "2026-06-30T14:15:33.651180+00:00"
      },
      {
        "title": "UK’s Starmer announces 300-billion-pound defence investment plan",
        "url": "https://www.aljazeera.com/economy/2026/6/30/uks-starmer-announces-300-billion-pound-defence-investment-plan?traffic_source=rss",
        "source": "Al Jazeera",
        "translated": false,
        "category": "mundo",
        "summary": "",
        "why": "",
        "impact": "",
        "impact_level": "médio",
        "breaking": false,
        "recomendacao": false,
        "enriched": false,
        "date": "2026-06-30T14:15:33.651180+00:00"
      },
      {
        "title": "África do Sul: manifestantes exigem saída de migrantes sem documentos",
        "url": "http://pt.euronews.com/video/2026/06/30/africa-do-sul-manifestantes-exigem-saida-de-migrantes-sem-documentos",
        "source": "Euronews PT",
        "translated": false,
        "category": "mundo",
        "summary": "",
        "why": "",
        "impact": "",
        "impact_level": "médio",
        "breaking": false,
        "recomendacao": false,
        "enriched": false,
        "date": "2026-06-30T14:15:33.651180+00:00"
      },
      {
        "title": "Espanha: milhares banhados em vinho em festival icónico",
        "url": "http://pt.euronews.com/video/2026/06/30/espanha-milhares-banhados-em-vinho-em-festival-iconico",
        "source": "Euronews PT",
        "translated": false,
        "category": "mundo",
        "summary": "",
        "why": "",
        "impact": "",
        "impact_level": "médio",
        "breaking": false,
        "recomendacao": false,
        "enriched": false,
        "date": "2026-06-30T14:15:33.651180+00:00"
      },
      {
        "title": "Enviados dos EUA Witkoff e Kushner chegam ao Qatar para novas conversações sobre Irão",
        "url": "http://pt.euronews.com/2026/06/30/enviados-dos-eua-witkoff-e-kushner-chegam-ao-qatar-para-novas-conversacoes-sobre-irao",
        "source": "Euronews PT",
        "translated": false,
        "category": "mundo",
        "summary": "",
        "why": "",
        "impact": "",
        "impact_level": "médio",
        "breaking": false,
        "recomendacao": false,
        "enriched": false,
        "date": "2026-06-30T14:15:33.651180+00:00"
      },
      {
        "title": "France records an extra 300 deaths during May heatwave",
        "url": "https://www.lemonde.fr/en/health/article/2026/06/30/france-records-an-extra-300-deaths-during-may-heatwave_6755011_14.html",
        "source": "Le Monde EN",
        "translated": false,
        "category": "mundo",
        "summary": "",
        "why": "",
        "impact": "",
        "impact_level": "médio",
        "breaking": false,
        "recomendacao": false,
        "enriched": false,
        "date": "2026-06-30T14:15:33.651180+00:00"
      },
      {
        "title": "Serena Williams returns to Wimbledon, in a comeback raising questions",
        "url": "https://www.lemonde.fr/en/sports/article/2026/06/30/serena-williams-returns-to-wimbledon-in-a-comeback-raising-questions_6755008_9.html",
        "source": "Le Monde EN",
        "translated": false,
        "category": "mundo",
        "summary": "",
        "why": "",
        "impact": "",
        "impact_level": "médio",
        "breaking": false,
        "recomendacao": false,
        "enriched": false,
        "date": "2026-06-30T14:15:33.651180+00:00"
      },
      {
        "title": "EU to implement trade deal with US starting Wednesday",
        "url": "https://www.lemonde.fr/en/international/article/2026/06/30/eu-to-implement-trade-deal-with-us-starting-wednesday_6755007_4.html",
        "source": "Le Monde EN",
        "translated": false,
        "category": "mundo",
        "summary": "",
        "why": "",
        "impact": "",
        "impact_level": "médio",
        "breaking": false,
        "recomendacao": false,
        "enriched": false,
        "date": "2026-06-30T14:15:33.651180+00:00"
      },
      {
        "title": "US birthright citizenship: What changes if it's removed?",
        "url": "https://www.dw.com/en/us-birthright-citizenship-what-changes-if-it-s-removed/a-77773604?maca=en-rss-en-all-1573-rdf",
        "source": "DW News",
        "translated": false,
        "category": "mundo",
        "summary": "",
        "why": "",
        "impact": "",
        "impact_level": "médio",
        "breaking": false,
        "recomendacao": false,
        "enriched": false,
        "date": "2026-06-30T14:15:33.651180+00:00"
      },
      {
        "title": "'Under siege': Uganda's army chief clamps down on the press",
        "url": "https://www.dw.com/en/under-siege-uganda-s-army-chief-clamps-down-on-the-press/a-77769666?maca=en-rss-en-all-1573-rdf",
        "source": "DW News",
        "translated": false,
        "category": "mundo",
        "summary": "",
        "why": "",
        "impact": "",
        "impact_level": "médio",
        "breaking": false,
        "recomendacao": false,
        "enriched": false,
        "date": "2026-06-30T14:15:33.651180+00:00"
      },
      {
        "title": "Will alleged crime ties damage Serbia's ruling party?",
        "url": "https://www.dw.com/en/will-alleged-crime-ties-damage-serbia-s-ruling-party/a-77772788?maca=en-rss-en-all-1573-rdf",
        "source": "DW News",
        "translated": false,
        "category": "mundo",
        "summary": "",
        "why": "",
        "impact": "",
        "impact_level": "médio",
        "breaking": false,
        "recomendacao": false,
        "enriched": false,
        "date": "2026-06-30T14:15:33.651180+00:00"
      }
    ],
    "economia": [
      {
        "title": "Turkey’s economic plan to win from the Iran war",
        "url": "https://www.economist.com/finance-and-economics/2026/06/29/turkeys-economic-plan-to-win-from-the-iran-war",
        "source": "The Economist",
        "translated": false,
        "category": "economia",
        "summary": "",
        "why": "",
        "impact": "",
        "impact_level": "médio",
        "breaking": false,
        "recomendacao": false,
        "enriched": false,
        "date": "2026-06-30T14:15:33.651180+00:00"
      },
      {
        "title": "China cracks down on rule-bending offshore investments",
        "url": "https://www.economist.com/finance-and-economics/2026/06/28/china-cracks-down-on-rule-bending-offshore-investments",
        "source": "The Economist",
        "translated": false,
        "category": "economia",
        "summary": "",
        "why": "",
        "impact": "",
        "impact_level": "médio",
        "breaking": false,
        "recomendacao": false,
        "enriched": false,
        "date": "2026-06-30T14:15:33.651180+00:00"
      },
      {
        "title": "Will AI lower interest rates?",
        "url": "https://www.economist.com/finance-and-economics/2026/06/25/will-ai-lower-interest-rates",
        "source": "The Economist",
        "translated": false,
        "category": "economia",
        "summary": "",
        "why": "",
        "impact": "",
        "impact_level": "médio",
        "breaking": false,
        "recomendacao": false,
        "enriched": false,
        "date": "2026-06-30T14:15:33.651180+00:00"
      },
      {
        "title": "Schwab CEO on Why They Keep Fees Low",
        "url": "https://www.bloomberg.com/news/videos/2026-06-30/schwab-ceo-on-why-they-keep-fees-low-video",
        "source": "Bloomberg",
        "translated": false,
        "category": "economia",
        "summary": "",
        "why": "",
        "impact": "",
        "impact_level": "médio",
        "breaking": false,
        "recomendacao": false,
        "enriched": false,
        "date": "2026-06-30T14:15:33.651180+00:00"
      },
      {
        "title": "US Stocks Mixed as Indexes Head for Best Quarter Since 2020",
        "url": "https://www.bloomberg.com/news/articles/2026-06-30/us-stocks-mixed-as-indexes-head-for-best-quarter-since-2020",
        "source": "Bloomberg",
        "translated": false,
        "category": "economia",
        "summary": "",
        "why": "",
        "impact": "",
        "impact_level": "médio",
        "breaking": false,
        "recomendacao": false,
        "enriched": false,
        "date": "2026-06-30T14:15:33.651180+00:00"
      },
      {
        "title": "UK ‘Minded to Intervene’ in Paramount’s Warner Bros. Deal Over Media Ownership Concerns",
        "url": "https://www.bloomberg.com/news/articles/2026-06-30/uk-minded-to-intervene-in-paramount-s-deal-for-warner-bros",
        "source": "Bloomberg",
        "translated": false,
        "category": "economia",
        "summary": "",
        "why": "",
        "impact": "",
        "impact_level": "médio",
        "breaking": false,
        "recomendacao": false,
        "enriched": false,
        "date": "2026-06-30T14:15:33.651180+00:00"
      },
      {
        "title": "Qatar nega a existência de negociações diretas entre Irão e Estados Unidos nos próximos dias",
        "url": "https://www.dn.pt/internacional/qatar-nega-a-existncia-de-negociaes-diretas-entre-iro-e-estados-unidos-nos-prximos-dias",
        "source": "Dinheiro Vivo",
        "translated": false,
        "category": "economia",
        "summary": "",
        "why": "",
        "impact": "",
        "impact_level": "médio",
        "breaking": false,
        "recomendacao": false,
        "enriched": false,
        "date": "2026-06-30T14:15:33.651180+00:00"
      },
      {
        "title": "Pesquisa revela que jovens brasileiros desconhecem a política sem redes sociais",
        "url": "https://dnbrasil.dn.pt/pesquisa-revela-que-jovens-brasileiros-desconhecem-a-poltica-sem-redes-sociais",
        "source": "Dinheiro Vivo",
        "translated": false,
        "category": "economia",
        "summary": "",
        "why": "",
        "impact": "",
        "impact_level": "médio",
        "breaking": false,
        "recomendacao": false,
        "enriched": false,
        "date": "2026-06-30T14:15:33.651180+00:00"
      },
      {
        "title": "PSP tem novos oficiais",
        "url": "https://www.dn.pt/sociedade/psp-tem-novos-oficiais",
        "source": "Dinheiro Vivo",
        "translated": false,
        "category": "economia",
        "summary": "",
        "why": "",
        "impact": "",
        "impact_level": "médio",
        "breaking": false,
        "recomendacao": false,
        "enriched": false,
        "date": "2026-06-30T14:15:33.651180+00:00"
      },
      {
        "title": "Wall Street arranca dividida à espera de maior definição sobre Irão",
        "url": "https://www.jornaldenegocios.pt/mercados/mercados-num-minuto/detalhe/recuperacao-em-wall-street-anima-indices-asiaticos-tiveram-melhor-trimestre-em-quase-17-anos",
        "source": "Jornal de Negócios",
        "translated": false,
        "category": "economia",
        "summary": "",
        "why": "",
        "impact": "",
        "impact_level": "médio",
        "breaking": false,
        "recomendacao": false,
        "enriched": false,
        "date": "2026-06-30T14:15:33.651180+00:00"
      },
      {
        "title": "Euforia na IA? Bolha só se os lucros não acompanharem mega-investimentos",
        "url": "https://www.jornaldenegocios.pt/mercados/bolsa/detalhe/euforia-na-ia-bolha-so-se-os-lucros-nao-acompanharem-mega-investimentos",
        "source": "Jornal de Negócios",
        "translated": false,
        "category": "economia",
        "summary": "",
        "why": "",
        "impact": "",
        "impact_level": "médio",
        "breaking": false,
        "recomendacao": false,
        "enriched": false,
        "date": "2026-06-30T14:15:33.651180+00:00"
      },
      {
        "title": "O Negócios pergunta. Maioria concorda com a criação de um fundo soberano português",
        "url": "https://www.jornaldenegocios.pt/empresas/media/o-negocios/detalhe/o-negocios-pergunta-maioria-concorda-com-a-criacao-de-um-fundo-soberano-portugues",
        "source": "Jornal de Negócios",
        "translated": false,
        "category": "economia",
        "summary": "",
        "why": "",
        "impact": "",
        "impact_level": "médio",
        "breaking": false,
        "recomendacao": false,
        "enriched": false,
        "date": "2026-06-30T14:15:33.651180+00:00"
      },
      {
        "title": "Ukrainian tycoon injured in Monaco bomb attack",
        "url": "https://www.ft.com/content/7455e85b-7389-49dd-b7c8-f145f79e7f0b",
        "source": "Financial Times",
        "translated": false,
        "category": "economia",
        "summary": "",
        "why": "",
        "impact": "",
        "impact_level": "médio",
        "breaking": false,
        "recomendacao": false,
        "enriched": false,
        "date": "2026-06-30T14:15:33.651180+00:00"
      },
      {
        "title": "Ukraine argues it can legally attack Russia’s shadow fleet",
        "url": "https://www.ft.com/content/d0f82c05-c35f-4e0f-b452-f61dc8a7e697",
        "source": "Financial Times",
        "translated": false,
        "category": "economia",
        "summary": "",
        "why": "",
        "impact": "",
        "impact_level": "médio",
        "breaking": false,
        "recomendacao": false,
        "enriched": false,
        "date": "2026-06-30T14:15:33.651180+00:00"
      },
      {
        "title": "Gold heads for worst quarter in more than a decade as retail frenzy fades",
        "url": "https://www.ft.com/content/ca75b117-f085-45be-95c1-7397d3b0797a",
        "source": "Financial Times",
        "translated": false,
        "category": "economia",
        "summary": "",
        "why": "",
        "impact": "",
        "impact_level": "médio",
        "breaking": false,
        "recomendacao": false,
        "enriched": false,
        "date": "2026-06-30T14:15:33.651180+00:00"
      }
    ],
    "portfolio": [
      {
        "title": "Replimune: Stock Buoyant On Third Try At RP1 Approval - FDA AdCom May Be Crucial",
        "url": "https://seekingalpha.com/article/4918850-replimune-stock-buoyant-on-third-try-at-rp1-approval-fda-adcom-may-be-crucial?source=feed_all_articles",
        "source": "Seeking Alpha",
        "translated": false,
        "category": "portfolio",
        "summary": "",
        "why": "",
        "impact": "",
        "impact_level": "médio",
        "breaking": false,
        "recomendacao": false,
        "enriched": false,
        "date": "2026-06-30T14:15:33.651180+00:00"
      },
      {
        "title": "Thungela Resources Limited (TNGRF) Discusses Pre-Close Update, Market Impacts of Middle East Conflict, and Coal Price Trends Transcript",
        "url": "https://seekingalpha.com/article/4918808-thungela-resources-limited-tngrf-discusses-pre-close-update-market-impacts-of-middle-east?source=feed_all_articles",
        "source": "Seeking Alpha",
        "translated": false,
        "category": "portfolio",
        "summary": "",
        "why": "",
        "impact": "",
        "impact_level": "médio",
        "breaking": false,
        "recomendacao": false,
        "enriched": false,
        "date": "2026-06-30T14:15:33.651180+00:00"
      },
      {
        "title": "Nickel Miners News For The Month Of June 2026",
        "url": "https://seekingalpha.com/article/4918849-nickel-miners-news-for-month-of-june-2026?source=feed_all_articles",
        "source": "Seeking Alpha",
        "translated": false,
        "category": "portfolio",
        "summary": "",
        "why": "",
        "impact": "",
        "impact_level": "médio",
        "breaking": false,
        "recomendacao": false,
        "enriched": false,
        "date": "2026-06-30T14:15:33.651180+00:00"
      }
    ],
    "tecnologia": [
      {
        "title": "Your brand deserves its own stage — Side Events at TechCrunch Disrupt 2026",
        "url": "https://techcrunch.com/2026/06/30/your-brand-deserves-its-own-stage-side-events-at-techcrunch-disrupt-2026/",
        "source": "TechCrunch",
        "translated": false,
        "category": "tecnologia",
        "summary": "",
        "why": "",
        "impact": "",
        "impact_level": "médio",
        "breaking": false,
        "recomendacao": false,
        "enriched": false,
        "date": "2026-06-30T14:15:33.651180+00:00"
      },
      {
        "title": "Lumo, Proton’s privacy-focused AI chatbot, gets an upgrade",
        "url": "https://techcrunch.com/2026/06/30/lumo-protons-privacy-focused-ai-chatbot-gets-an-upgrade/",
        "source": "TechCrunch",
        "translated": false,
        "category": "tecnologia",
        "summary": "",
        "why": "",
        "impact": "",
        "impact_level": "médio",
        "breaking": false,
        "recomendacao": false,
        "enriched": false,
        "date": "2026-06-30T14:15:33.651180+00:00"
      },
      {
        "title": "Crypto exchange OKX wants AI agents to hire and pay each other",
        "url": "https://techcrunch.com/2026/06/30/crypto-exchange-okx-wants-ai-agents-to-hire-and-pay-each-other/",
        "source": "TechCrunch",
        "translated": false,
        "category": "tecnologia",
        "summary": "",
        "why": "",
        "impact": "",
        "impact_level": "médio",
        "breaking": false,
        "recomendacao": false,
        "enriched": false,
        "date": "2026-06-30T14:15:33.651180+00:00"
      },
      {
        "title": "The 2 Best Slushie Machines of 2026: Now With Soft Serve",
        "url": "https://www.wired.com/gallery/best-slushie-machines/",
        "source": "Wired",
        "translated": false,
        "category": "tecnologia",
        "summary": "",
        "why": "",
        "impact": "",
        "impact_level": "médio",
        "breaking": false,
        "recomendacao": false,
        "enriched": false,
        "date": "2026-06-30T14:15:33.651180+00:00"
      },
      {
        "title": "Bitdefender VPN Review: Fast and Affordable Privacy",
        "url": "https://www.wired.com/review/bitdefender-vpn/",
        "source": "Wired",
        "translated": false,
        "category": "tecnologia",
        "summary": "",
        "why": "",
        "impact": "",
        "impact_level": "médio",
        "breaking": false,
        "recomendacao": false,
        "enriched": false,
        "date": "2026-06-30T14:15:33.651180+00:00"
      },
      {
        "title": "Bernie Sanders Saw This Coming",
        "url": "https://www.wired.com/story/the-big-interview-podcast-senator-bernie-sanders/",
        "source": "Wired",
        "translated": false,
        "category": "tecnologia",
        "summary": "",
        "why": "",
        "impact": "",
        "impact_level": "médio",
        "breaking": false,
        "recomendacao": false,
        "enriched": false,
        "date": "2026-06-30T14:15:33.651180+00:00"
      },
      {
        "title": "iPhone 18 Pro ‘drop test’ leaks get yanked from X",
        "url": "https://www.theverge.com/tech/959474/iphone-18-pro-leaked-videos-pulled",
        "source": "The Verge",
        "translated": false,
        "category": "tecnologia",
        "summary": "",
        "why": "",
        "impact": "",
        "impact_level": "médio",
        "breaking": false,
        "recomendacao": false,
        "enriched": false,
        "date": "2026-06-30T14:15:33.651180+00:00"
      },
      {
        "title": "Meet the lawyer who beat Elon Musk — twice",
        "url": "https://www.theverge.com/column/959270/elon-musk-open-ai-bill-savitt-twitter",
        "source": "The Verge",
        "translated": false,
        "category": "tecnologia",
        "summary": "",
        "why": "",
        "impact": "",
        "impact_level": "médio",
        "breaking": false,
        "recomendacao": false,
        "enriched": false,
        "date": "2026-06-30T14:15:33.651180+00:00"
      },
      {
        "title": "This motor could be the future of e-bikes",
        "url": "https://www.theverge.com/news/959382/avinox-mg-concept-gobao-mgu-ecvt",
        "source": "The Verge",
        "translated": false,
        "category": "tecnologia",
        "summary": "",
        "why": "",
        "impact": "",
        "impact_level": "médio",
        "breaking": false,
        "recomendacao": false,
        "enriched": false,
        "date": "2026-06-30T14:15:33.651180+00:00"
      }
    ],
    "carreira": [
      {
        "title": "Will tech giants ever let us opt out of AI search features?",
        "url": "https://www.fastcompany.com/91561463/google-ai-overviews-users-opt-out-will-that-change",
        "source": "Fast Company",
        "translated": false,
        "category": "carreira",
        "summary": "",
        "why": "",
        "impact": "",
        "impact_level": "médio",
        "breaking": false,
        "recomendacao": false,
        "enriched": false,
        "date": "2026-06-30T14:15:33.651180+00:00"
      },
      {
        "title": "Here’s how to reserve your WhatsApp username—and why you should do it before the release date",
        "url": "https://www.fastcompany.com/91567304/whatsapp-usernames-release-date-nears-how-to-reserve-yours",
        "source": "Fast Company",
        "translated": false,
        "category": "carreira",
        "summary": "",
        "why": "",
        "impact": "",
        "impact_level": "médio",
        "breaking": false,
        "recomendacao": false,
        "enriched": false,
        "date": "2026-06-30T14:15:33.651180+00:00"
      },
      {
        "title": "How to Ensure Your Next CEO is Always in the Room",
        "url": "https://www.fastcompany.com/91566039/how-to-ensure-your-next-ceo-is-always-in-the-room",
        "source": "Fast Company",
        "translated": false,
        "category": "carreira",
        "summary": "",
        "why": "",
        "impact": "",
        "impact_level": "médio",
        "breaking": false,
        "recomendacao": false,
        "enriched": false,
        "date": "2026-06-30T14:15:33.651180+00:00"
      },
      {
        "title": "When Evaluating an M&A Opportunity, Consider the Broader Digital Ecosystem",
        "url": "/2026/06/when-evaluating-an-ma-opportunity-consider-the-broader-digital-ecosystem",
        "source": "HBR",
        "translated": false,
        "category": "carreira",
        "summary": "",
        "why": "",
        "impact": "",
        "impact_level": "médio",
        "breaking": false,
        "recomendacao": false,
        "enriched": false,
        "date": "2026-06-30T14:15:33.651180+00:00"
      },
      {
        "title": "How Top World Cup, NBA, and NFL Coaches Make Better Decisions Under Pressure",
        "url": "/podcast/2026/06/how-top-world-cup-nba-and-nfl-coaches-make-better-decisions-under-pressure",
        "source": "HBR",
        "translated": false,
        "category": "carreira",
        "summary": "",
        "why": "",
        "impact": "",
        "impact_level": "médio",
        "breaking": false,
        "recomendacao": false,
        "enriched": false,
        "date": "2026-06-30T14:15:33.651180+00:00"
      },
      {
        "title": "Your Talent Strategy Has to Keep Up with Your AI Transformation",
        "url": "/2026/06/your-talent-strategy-has-to-keep-up-with-your-ai-transformation",
        "source": "HBR",
        "translated": false,
        "category": "carreira",
        "summary": "",
        "why": "",
        "impact": "",
        "impact_level": "médio",
        "breaking": false,
        "recomendacao": false,
        "enriched": false,
        "date": "2026-06-30T14:15:33.651180+00:00"
      }
    ],
    "recomendacao": []
  },
  "summary": {
    "headline": "Briefing de 30 de Junho de 2026",
    "items": []
  },
  "connections": [],
  "stocks": [
    {
      "symbol": "AAPL",
      "label": "Apple",
      "price": 285.77,
      "change_pct": 1.43,
      "up": true
    },
    {
      "symbol": "MSFT",
      "label": "Microsoft",
      "price": 371.64,
      "change_pct": 0.83,
      "up": true
    },
    {
      "symbol": "NVDA",
      "label": "NVIDIA",
      "price": 197.18,
      "change_pct": 1.13,
      "up": true
    },
    {
      "symbol": "TSLA",
      "label": "Tesla",
      "price": 416.11,
      "change_pct": 1.04,
      "up": true
    },
    {
      "symbol": "AMZN",
      "label": "Amazon",
      "price": 238.92,
      "change_pct": -0.51,
      "up": false
    },
    {
      "symbol": "EURUSD=X",
      "label": "EUR/USD",
      "price": 1.14,
      "change_pct": 0.23,
      "up": true
    },
    {
      "symbol": "BTC-USD",
      "label": "Bitcoin",
      "price": 58922.01,
      "change_pct": -2.02,
      "up": false
    },
    {
      "symbol": "GC=F",
      "label": "Ouro",
      "price": 4043.4,
      "change_pct": 0.52,
      "up": true
    }
  ],
  "portfolio_analysis": {
    "total_change_pct": 0.33,
    "sentiment": "positivo",
    "what_happened": "Mercado em alta: Apple, Microsoft, NVIDIA sobem; Amazon, Bitcoin descem.",
    "what_to_do": "Manter posições.",
    "risks": "Volatilidade normal.",
    "tips": [
      {
        "risk": "baixo",
        "suggestion": "ETF de índice diversificado"
      },
      {
        "risk": "médio",
        "suggestion": "Acções de qualidade com dividendo"
      },
      {
        "risk": "alto",
        "suggestion": "Sem recomendação especulativa"
      }
    ]
  },
  "weekly_narrative": null
}